openai/__init__.py
openai/__main__.py
openai/_base_client.py
openai/_client.py
openai/_compat.py
openai/_constants.py
openai/_exceptions.py
openai/_files.py
openai/_legacy_response.py
openai/_models.py
openai/_module_client.py
openai/_qs.py
openai/_resource.py
openai/_response.py
openai/_streaming.py
openai/_types.py
openai/_version.py
openai/helpers.py
openai/pagination.py
openai/py.typed
openai/version.py
openai/_extras/__init__.py
openai/_extras/_common.py
openai/_extras/numpy_proxy.py
openai/_extras/pandas_proxy.py
openai/_utils/__init__.py
openai/_utils/_logs.py
openai/_utils/_proxy.py
openai/_utils/_reflection.py
openai/_utils/_streams.py
openai/_utils/_sync.py
openai/_utils/_transform.py
openai/_utils/_typing.py
openai/_utils/_utils.py
openai/cli/__init__.py
openai/cli/_cli.py
openai/cli/_errors.py
openai/cli/_models.py
openai/cli/_progress.py
openai/cli/_utils.py
openai/cli/_api/__init__.py
openai/cli/_api/_main.py
openai/cli/_api/audio.py
openai/cli/_api/completions.py
openai/cli/_api/files.py
openai/cli/_api/image.py
openai/cli/_api/models.py
openai/cli/_api/chat/__init__.py
openai/cli/_api/chat/completions.py
openai/cli/_tools/__init__.py
openai/cli/_tools/_main.py
openai/cli/_tools/fine_tunes.py
openai/cli/_tools/migrate.py
openai/helpers/__init__.py
openai/helpers/local_audio_player.py
openai/helpers/microphone.py
openai/lib/__init__.py
openai/lib/_old_api.py
openai/lib/_pydantic.py
openai/lib/_tools.py
openai/lib/_validators.py
openai/lib/azure.py
openai/lib/_parsing/__init__.py
openai/lib/_parsing/_completions.py
openai/lib/_parsing/_responses.py
openai/lib/streaming/__init__.py
openai/lib/streaming/_assistants.py
openai/lib/streaming/_deltas.py
openai/lib/streaming/chat/__init__.py
openai/lib/streaming/chat/_completions.py
openai/lib/streaming/chat/_events.py
openai/lib/streaming/chat/_types.py
openai/lib/streaming/responses/__init__.py
openai/lib/streaming/responses/_events.py
openai/lib/streaming/responses/_responses.py
openai_aipy-1.68.0.dist-info/METADATA
openai_aipy-1.68.0.dist-info/WHEEL
openai_aipy-1.68.0.dist-info/top_level.txt
openai_aipy-1.68.0.dist-info/RECORD
