Metadata-Version: 2.4
Name: openai-aipy
Version: 1.68.0
Summary: The official Python library for the openai API
Author-email: The QPYPI Team <qpypi@qpython.org>
License: MIT AND (Apache-2.0 OR BSD-2-Clause)
Project-URL: Homepage, https://qpypi.qpython.org/project/openai-aipy/
Classifier: Intended Audience :: Developers
Classifier: Intended Audience :: Education
Classifier: Intended Audience :: Information Technology
Classifier: Intended Audience :: End Users/Desktop
Classifier: License :: OSI Approved :: Apache Software License
Classifier: Operating System :: Android
Classifier: Programming Language :: Python
Classifier: Programming Language :: Python :: 3.12
Classifier: Topic :: Software Development
Requires-Python: ==3.12.*
Requires-Dist: typing-extensions-qpython
Requires-Dist: pydantic-qpython
Requires-Dist: jiter-qpython
Requires-Dist: httpx
Requires-Dist: annotated-types
Requires-Dist: anyio
Requires-Dist: certifi
Requires-Dist: distro
Requires-Dist: h11
Requires-Dist: httpcore
Requires-Dist: idna
Requires-Dist: tqdm
